README.rst
setup.cfg
setup.py
drigo/__init__.py
drigo/drigo.py
drigo.egg-info/PKG-INFO
drigo.egg-info/SOURCES.txt
drigo.egg-info/dependency_links.txt
drigo.egg-info/requires.txt
drigo.egg-info/top_level.txt