Metadata-Version: 1.1
Name: drigo
Version: 0.1.1
Summary: DRI GDAL/OGR Helper Functions
Home-page: https://github.com/DRI-WSWUP/drigo
Author: Charles Morton
Author-email: charles.g.morton@gmail.com
License: Apache
Download-URL: https://github.com/DRI-WSWUP/drigo/archive/v0.1.1.tar.gz
Keywords: GDAL OGR
Platform: UNKNOWN
Classifier: License :: OSI Approved :: Apache Software License
Classifier: Programming Language :: Python :: 2.7
Classifier: Programming Language :: Python :: 3.5
Classifier: Programming Language :: Python :: 3.6
